mkdocs_izsam_search/__init__.py
mkdocs_izsam_search/plugin.py
mkdocs_izsam_search/prebuild-index.js
mkdocs_izsam_search/search_index.py
mkdocs_izsam_search/lunr-language/lunr.ar.js
mkdocs_izsam_search/lunr-language/lunr.da.js
mkdocs_izsam_search/lunr-language/lunr.de.js
mkdocs_izsam_search/lunr-language/lunr.du.js
mkdocs_izsam_search/lunr-language/lunr.es.js
mkdocs_izsam_search/lunr-language/lunr.fi.js
mkdocs_izsam_search/lunr-language/lunr.fr.js
mkdocs_izsam_search/lunr-language/lunr.hu.js
mkdocs_izsam_search/lunr-language/lunr.it.js
mkdocs_izsam_search/lunr-language/lunr.ja.js
mkdocs_izsam_search/lunr-language/lunr.jp.js
mkdocs_izsam_search/lunr-language/lunr.multi.js
mkdocs_izsam_search/lunr-language/lunr.nl.js
mkdocs_izsam_search/lunr-language/lunr.no.js
mkdocs_izsam_search/lunr-language/lunr.pt.js
mkdocs_izsam_search/lunr-language/lunr.ro.js
mkdocs_izsam_search/lunr-language/lunr.ru.js
mkdocs_izsam_search/lunr-language/lunr.stemmer.support.js
mkdocs_izsam_search/lunr-language/lunr.sv.js
mkdocs_izsam_search/lunr-language/lunr.th.js
mkdocs_izsam_search/lunr-language/lunr.tr.js
mkdocs_izsam_search/lunr-language/lunr.vi.js
mkdocs_izsam_search/lunr-language/tinyseg.js
mkdocs_izsam_search/templates/search/lunr.js
mkdocs_izsam_search/templates/search/main.js
mkdocs_izsam_search/templates/search/worker.js
mkdocs_izsam_search-0.1.9.dist-info/LICENCE.txt
mkdocs_izsam_search-0.1.9.dist-info/METADATA
mkdocs_izsam_search-0.1.9.dist-info/WHEEL
mkdocs_izsam_search-0.1.9.dist-info/entry_points.txt
mkdocs_izsam_search-0.1.9.dist-info/top_level.txt
mkdocs_izsam_search-0.1.9.dist-info/RECORD
