Metadata-Version: 2.1
Name: mkdocs-izsam-search
Version: 0.1.9
Summary: MkDocs plugin to extend search functions
Home-page: 
Download-URL: 
Author: Alessandro De Luca
Author-email: al.deluca@izs.it
License: MIT
Keywords: MkDocs,Search
Requires-Python: >=3.8
License-File: LICENCE.txt
Requires-Dist: mkdocs>=1.0.4
